[{"name": "baby", "value": 6680}, {"name": "br", "value": 5685}, {"name": "pacifier", "value": 5143}, {"name": "love", "value": 4089}, {"name": "loves", "value": 3230}, {"name": "pacifiers", "value": 3202}, {"name": "product", "value": 2711}, {"name": "son", "value": 2705}, {"name": "easy", "value": 2592}, {"name": "daughter", "value": 2510}, {"name": "Stars", "value": 2271}, {"name": "cute", "value": 2023}, {"name": "time", "value": 1994}, {"name": "mouth", "value": 1986}, {"name": "bought", "value": 1957}, {"name": "Five", "value": 1878}, {"name": "months", "value": 1830}, {"name": "stars", "value": 1577}, {"name": "2", "value": 1533}, {"name": "34", "value": 1424}, {"name": "seat", "value": 1397}, {"name": "nice", "value": 1350}, {"name": "perfect", "value": 1343}, {"name": "3", "value": 1298}, {"name": "Great", "value": 1259}, {"name": "month", "value": 1242}, {"name": "buy", "value": 1236}, {"name": "quality", "value": 1218}, {"name": "bag", "value": 1199}, {"name": "hold", "value": 1195}, {"name": "recommend", "value": 1177}, {"name": "clean", "value": 1085}, {"name": "loved", "value": 1080}, {"name": "size", "value": 1059}, {"name": "gift", "value": 1048}, {"name": "soft", "value": 1031}, {"name": "car", "value": 1031}, {"name": "paci", "value": 1002}, {"name": "babies", "value": 998}, {"name": "Love", "value": 998}, {"name": "night", "value": 991}, {"name": "price", "value": 968}, {"name": "5", "value": 941}, {"name": "nipple", "value": 931}, {"name": "easily", "value": 911}, {"name": "fit", "value": 908}, {"name": "hard", "value": 871}, {"name": "4", "value": 857}, {"name": "child", "value": 838}, {"name": "likes", "value": 789}, {"name": "crib", "value": 766}, {"name": "toy", "value": 759}, {"name": "happy", "value": 750}, {"name": "purchased", "value": 748}, {"name": "diaper", "value": 737}, {"name": "6", "value": 715}, {"name": "bit", "value": 710}, {"name": "stroller", "value": 697}, {"name": "item", "value": 695}, {"name": "bottles", "value": 670}, {"name": "1", "value": 668}, {"name": "favorite", "value": 666}, {"name": "It's", "value": 659}, {"name": "wash", "value": 654}, {"name": "sleep", "value": 650}, {"name": "pretty", "value": 637}, {"name": "hospital", "value": 635}, {"name": "newborn", "value": 634}, {"name": "water", "value": 633}, {"name": "lot", "value": 632}, {"name": "super", "value": 630}, {"name": "baby's", "value": 629}, {"name": "easier", "value": 628}, {"name": "plastic", "value": 622}, {"name": "bottle", "value": 621}, {"name": "animal", "value": 619}, {"name": "worth", "value": 618}, {"name": "colors", "value": 610}, {"name": "color", "value": 600}, {"name": "shower", "value": 593}, {"name": "day", "value": 592}, {"name": "kids", "value": 582}, {"name": "brand", "value": 580}, {"name": ":", "value": 578}, {"name": "So", "value": 568}, {"name": "monitor", "value": 561}, {"name": "light", "value": 540}, {"name": "play", "value": 540}, {"name": "set", "value": 537}, {"name": "design", "value": 536}, {"name": "received", "value": 531}, {"name": "purchase", "value": 527}, {"name": "I'm", "value": 504}, {"name": "money", "value": 487}, {"name": "shape", "value": 483}, {"name": "weeks", "value": 479}, {"name": "stay", "value": 479}, {"name": "cover", "value": 478}, {"name": "fits", "value": 478}, {"name": "Baby", "value": 469}, {"name": "idea", "value": 462}, {"name": "dark", "value": 457}, {"name": "times", "value": 453}, {"name": "Very", "value": 442}, {"name": "fall", "value": 440}, {"name": "girl", "value": 437}, {"name": "Not", "value": 436}, {"name": "Our", "value": 430}, {"name": "pink", "value": 425}, {"name": "feel", "value": 425}, {"name": "top", "value": 418}, {"name": "started", "value": 416}, {"name": "highly", "value": 413}, {"name": "stuffed", "value": 411}, {"name": "binky", "value": 410}, {"name": "comfortable", "value": 409}, {"name": "reviews", "value": 406}, {"name": "adorable", "value": 404}, {"name": "born", "value": 398}, {"name": "bed", "value": 397}, {"name": "house", "value": 395}, {"name": "chair", "value": 393}, {"name": "hand", "value": 391}, {"name": "glow", "value": 381}, {"name": "boy", "value": 380}, {"name": "picture", "value": 379}, {"name": "soothie", "value": 377}, {"name": "piece", "value": 376}, {"name": "pack", "value": 375}, {"name": "grandson", "value": 371}, {"name": "attached", "value": 370}, {"name": "But", "value": 368}, {"name": "hands", "value": 368}, {"name": "absolutely", "value": 367}, {"name": "buying", "value": 366}, {"name": "inside", "value": 363}, {"name": "fine", "value": 359}, {"name": "A", "value": 357}, {"name": "mattress", "value": 357}, {"name": "expected", "value": 357}, {"name": "sturdy", "value": 357}, {"name": "toys", "value": 357}, {"name": "Good", "value": 354}, {"name": "infant", "value": 351}, {"name": "If", "value": 350}, {"name": "extra", "value": 350}, {"name": "safe", "value": 346}, {"name": "store", "value": 343}, {"name": "Cute", "value": 341}, {"name": "material", "value": 340}, {"name": "cup", "value": 337}, {"name": "helps", "value": 336}, {"name": "teething", "value": 335}, {"name": "awesome", "value": 333}, {"name": "10", "value": 328}, {"name": "head", "value": 327}, {"name": "toddler", "value": 327}, {"name": "regular", "value": 324}, {"name": "perfectly", "value": 322}, {"name": "gate", "value": 319}, {"name": "wubbanub", "value": 318}, {"name": "great!", "value": 318}, {"name": "fun", "value": 317}, {"name": "weight", "value": 316}, {"name": "free", "value": 316}, {"name": "monkey", "value": 314}, {"name": "Best", "value": 314}, {"name": "disappointed", "value": 314}, {"name": "week", "value": 314}, {"name": "excellent", "value": 314}, {"name": "lost", "value": 309}, {"name": "couple", "value": 309}, {"name": "handle", "value": 309}, {"name": "kid", "value": 308}, {"name": "giraffe", "value": 307}, {"name": "Soothie", "value": 306}, {"name": "days", "value": 304}, {"name": "suck", "value": 302}, {"name": "these!", "value": 302}, {"name": "bad", "value": 299}, {"name": "box", "value": 298}, {"name": "heavy", "value": 298}, {"name": "sucking", "value": 294}, {"name": "blue", "value": 294}, {"name": "life", "value": 293}, {"name": "dry", "value": 293}, {"name": "difficult", "value": 293}, {"name": "When", "value": 292}, {"name": "bottom", "value": 291}, {"name": "bags", "value": 290}, {"name": "cute!", "value": 289}, {"name": "And", "value": 289}, {"name": "amazon", "value": 285}, {"name": "she's", "value": 284}, {"name": "MAM", "value": 282}, {"name": "friend", "value": 278}, {"name": "diapers", "value": 277}, {"name": "washing", "value": 276}, {"name": "durable", "value": 274}, {"name": "arrived", "value": 274}, {"name": "product!", "value": 272}, {"name": "decided", "value": 271}, {"name": "holding", "value": 271}, {"name": "grab", "value": 271}, {"name": "fast", "value": 270}, {"name": "floor", "value": 269}, {"name": "husband", "value": 267}, {"name": "falls", "value": 266}, {"name": "mom", "value": 266}, {"name": "Perfect", "value": 266}, {"name": "breast", "value": 264}, {"name": "them!", "value": 264}, {"name": "pump", "value": 264}, {"name": "takes", "value": 263}, {"name": "front", "value": 261}, {"name": "reason", "value": 261}, {"name": "Wubbanub", "value": 260}, {"name": "8", "value": 260}, {"name": "middle", "value": 259}, {"name": "close", "value": 259}, {"name": "holds", "value": 258}, {"name": "rubber", "value": 257}, {"name": "pillow", "value": 257}, {"name": "bigger", "value": 256}, {"name": "stays", "value": 256}, {"name": "job", "value": 256}, {"name": "minutes", "value": 255}, {"name": "children", "value": 255}, {"name": "issue", "value": 255}, {"name": "wonderful", "value": 254}, {"name": "changing", "value": 253}, {"name": "Pacifier", "value": 252}, {"name": "glad", "value": 251}, {"name": "parents", "value": 251}, {"name": "cheap", "value": 248}, {"name": "blanket", "value": 248}, {"name": "I've", "value": 247}, {"name": "brands", "value": 247}, {"name": "nose", "value": 246}, {"name": "green", "value": 246}, {"name": "asleep", "value": 245}, {"name": "natural", "value": 244}, {"name": "expensive", "value": 242}, {"name": "recommended", "value": 242}, {"name": "7", "value": 240}, {"name": "type", "value": 239}, {"name": "read", "value": 238}, {"name": "milk", "value": 238}, {"name": "air", "value": 238}, {"name": "sound", "value": 237}, {"name": "machine", "value": 236}, {"name": "shipping", "value": 235}, {"name": "smell", "value": 234}, {"name": "food", "value": 233}, {"name": "straps", "value": 231}, {"name": "products", "value": 231}, {"name": "LOVE", "value": 231}, {"name": "cups", "value": 231}, {"name": "people", "value": 230}, {"name": "chew", "value": 230}, {"name": "Four", "value": 230}, {"name": "looked", "value": 229}, {"name": "friends", "value": 228}, {"name": "0", "value": 228}, {"name": "keeping", "value": 228}, {"name": "throw", "value": 227}, {"name": "huge", "value": 227}, {"name": "pull", "value": 226}, {"name": "stick", "value": 225}, {"name": "pad", "value": 224}, {"name": "issues", "value": 224}, {"name": "Avent", "value": 224}, {"name": "Also", "value": 223}, {"name": "fabric", "value": 223}, {"name": "deal", "value": 220}, {"name": "style", "value": 220}, {"name": "granddaughter", "value": 218}, {"name": "son's", "value": 218}, {"name": "sleeping", "value": 216}, {"name": "review", "value": 216}, {"name": "Just", "value": 216}, {"name": "You", "value": 215}, {"name": "bear", "value": 215}, {"name": "carry", "value": 214}, {"name": "One", "value": 213}, {"name": "cloth", "value": 212}, {"name": "WubbaNub", "value": 210}, {"name": "completely", "value": 209}, {"name": "leave", "value": 209}, {"name": "pleased", "value": 209}, {"name": "pacis", "value": 208}, {"name": "teeth", "value": 207}, {"name": "travel", "value": 206}, {"name": "As", "value": 206}, {"name": "space", "value": 205}, {"name": "washed", "value": 203}, {"name": "dog", "value": 203}, {"name": "move", "value": 203}, {"name": "Easy", "value": 202}, {"name": "silicone", "value": 201}, {"name": "feature", "value": 199}, {"name": "change", "value": 199}, {"name": "nipples", "value": 199}, {"name": "star", "value": 199}, {"name": "lose", "value": 198}, {"name": "larger", "value": 196}, {"name": "care", "value": 195}, {"name": "pieces", "value": 194}, {"name": "simple", "value": 194}, {"name": "this!", "value": 194}, {"name": "install", "value": 193}, {"name": "attach", "value": 192}, {"name": "falling", "value": 191}, {"name": "Now", "value": 191}, {"name": "However", "value": 190}, {"name": "white", "value": 190}, {"name": "wipes", "value": 190}, {"name": "safety", "value": 190}, {"name": "items", "value": 190}, {"name": "putting", "value": 188}, {"name": "wait", "value": 188}, {"name": "amazing", "value": 188}, {"name": "table", "value": 187}, {"name": "feeding", "value": 187}, {"name": "bright", "value": 186}, {"name": "cut", "value": 186}, {"name": "quick", "value": 186}, {"name": "half", "value": 186}, {"name": "legs", "value": 185}, {"name": "Only", "value": 185}, {"name": "ago", "value": 185}, {"name": "swing", "value": 182}, {"name": "stuff", "value": 181}, {"name": "fan", "value": 181}, {"name": "short", "value": 181}, {"name": "spit", "value": 180}, {"name": "No", "value": 180}, {"name": "warm", "value": 179}, {"name": "mind", "value": 179}, {"name": "return", "value": 179}, {"name": "stores", "value": 179}, {"name": "finally", "value": 178}, {"name": "package", "value": 178}, {"name": "wet", "value": 178}, {"name": "expecting", "value": 177}, {"name": "base", "value": 177}, {"name": "animals", "value": 177}, {"name": "system", "value": 176}, {"name": "option", "value": 176}, {"name": "gifts", "value": 176}, {"name": "worry", "value": 176}, {"name": "hot", "value": 174}, {"name": "sit", "value": 174}, {"name": "flat", "value": 173}, {"name": "handy", "value": 173}, {"name": "wall", "value": 172}, {"name": "wrong", "value": 172}, {"name": "prefers", "value": 172}, {"name": "cleaning", "value": 172}, {"name": "strap", "value": 171}, {"name": "replace", "value": 170}, {"name": "Amazon", "value": 170}, {"name": "hours", "value": 170}, {"name": "real", "value": 170}, {"name": "9", "value": 170}, {"name": "elephant", "value": 169}, {"name": "tiny", "value": 169}, {"name": "wear", "value": 169}, {"name": "start", "value": 168}, {"name": "stuck", "value": 168}, {"name": "chest", "value": 168}, {"name": "strong", "value": 168}, {"name": "wife", "value": 167}, {"name": "constantly", "value": 167}, {"name": "lots", "value": 165}, {"name": "hit", "value": 165}, {"name": "twins", "value": 164}, {"name": "guess", "value": 164}, {"name": "company", "value": 164}, {"name": "helped", "value": 164}, {"name": "leak", "value": 163}, {"name": "cool", "value": 163}, {"name": "carrier", "value": 163}, {"name": "bath", "value": 162}, {"name": "beautiful", "value": 162}, {"name": "replacement", "value": 162}, {"name": "newborns", "value": 161}, {"name": "clip", "value": 161}, {"name": "suction", "value": 161}, {"name": "comfort", "value": 160}, {"name": "waste", "value": 160}, {"name": "latch", "value": 159}, {"name": "!", "value": 159}, {"name": "guy", "value": 158}, {"name": "daughter's", "value": 158}, {"name": "broke", "value": 158}, {"name": "feet", "value": 157}, {"name": "boys", "value": 157}, {"name": "soothies", "value": 157}, {"name": "family", "value": 157}, {"name": "pictures", "value": 157}, {"name": "too!", "value": 156}, {"name": "binkies", "value": 156}, {"name": "music", "value": 156}, {"name": "thin", "value": 155}, {"name": "After", "value": 155}, {"name": "hole", "value": 155}, {"name": "held", "value": 155}, {"name": "funny", "value": 153}, {"name": "tight", "value": 153}, {"name": "12", "value": 153}, {"name": "dirty", "value": 152}, {"name": "carseat", "value": 152}, {"name": "live", "value": 152}, {"name": "service", "value": 152}, {"name": "noise", "value": 152}, {"name": "break", "value": 151}, {"name": "seats", "value": 151}, {"name": "potty", "value": 151}, {"name": "nephew", "value": 150}, {"name": "holes", "value": 150}, {"name": "pacifiers!", "value": 149}, {"name": "pacifier!", "value": 149}, {"name": "mine", "value": 148}, {"name": "extremely", "value": 148}, {"name": "camera", "value": 148}, {"name": "breastfed", "value": 148}, {"name": "unit", "value": 147}, {"name": "parent", "value": 147}, {"name": "prefer", "value": 146}, {"name": "dropped", "value": 146}, {"name": "pick", "value": 145}, {"name": "Nice", "value": 145}, {"name": "breastfeeding", "value": 145}, {"name": "covers", "value": 144}, {"name": "age", "value": 144}, {"name": "battery", "value": 144}, {"name": "purpose", "value": 144}, {"name": "teether", "value": 144}, {"name": "complaint", "value": 143}, {"name": "cheaper", "value": 143}, {"name": "push", "value": 143}, {"name": "remove", "value": 143}, {"name": "Super", "value": 142}, {"name": "totally", "value": 141}, {"name": "Nuk", "value": 140}, {"name": "harder", "value": 140}, {"name": "20", "value": 140}, {"name": "shaped", "value": 139}, {"name": "pictured", "value": 139}, {"name": "tub", "value": 138}, {"name": "tray", "value": 138}, {"name": "nursing", "value": 138}, {"name": "red", "value": 138}, {"name": "feels", "value": 137}, {"name": "helpful", "value": 137}, {"name": "sippy", "value": 137}, {"name": "pop", "value": 136}, {"name": "instructions", "value": 136}, {"name": "noticed", "value": 136}, {"name": "puppy", "value": 136}, {"name": "poor", "value": 136}, {"name": "convenient", "value": 136}, {"name": "lightweight", "value": 135}, {"name": "plush", "value": 135}, {"name": "excited", "value": 135}, {"name": "hang", "value": 135}, {"name": "customer", "value": 135}, {"name": "ready", "value": 135}, {"name": "left", "value": 134}, {"name": "difference", "value": 133}, {"name": "daughters", "value": 133}, {"name": "dishwasher", "value": 133}, {"name": "lamb", "value": 132}, {"name": "pain", "value": 132}, {"name": "niece", "value": 131}, {"name": "secure", "value": 131}, {"name": "sleeps", "value": 131}, {"name": "sitting", "value": 130}, {"name": "hoping", "value": 130}, {"name": "pocket", "value": 130}, {"name": "wubbanubs", "value": 129}, {"name": "velcro", "value": 129}, {"name": "sheet", "value": 129}, {"name": "leaks", "value": 129}, {"name": "mat", "value": 128}, {"name": "nursery", "value": 128}, {"name": "clothes", "value": 128}, {"name": "playing", "value": 128}, {"name": "snap", "value": 128}, {"name": "ring", "value": 128}, {"name": "Bought", "value": 128}, {"name": "video", "value": 127}, {"name": "LOVES", "value": 127}, {"name": "purple", "value": 127}, {"name": "packaging", "value": 127}, {"name": "low", "value": 127}, {"name": "sheets", "value": 127}, {"name": "Wubbanubs", "value": 126}, {"name": "softer", "value": 126}, {"name": "book", "value": 126}, {"name": "batteries", "value": 126}, {"name": "Pacifiers", "value": 125}, {"name": "double", "value": 125}, {"name": "coming", "value": 125}, {"name": "original", "value": 124}, {"name": "orthodontic", "value": 124}, {"name": "hope", "value": 124}, {"name": "reach", "value": 124}, {"name": "stopped", "value": 123}, {"name": "supposed", "value": 123}, {"name": "For", "value": 123}, {"name": "figure", "value": 122}, {"name": "nicely", "value": 122}, {"name": "trouble", "value": 122}, {"name": "There", "value": 122}, {"name": "bulky", "value": 122}, {"name": "medela", "value": 122}, {"name": "annoying", "value": 121}, {"name": "loose", "value": 121}, {"name": "fell", "value": 121}, {"name": "storage", "value": 121}, {"name": "handles", "value": 120}, {"name": "position", "value": 120}, {"name": "sister", "value": 120}, {"name": "wipe", "value": 120}, {"name": "amount", "value": 120}, {"name": "addition", "value": 120}, {"name": "add", "value": 119}, {"name": "15", "value": 119}, {"name": "NOT", "value": 118}, {"name": "drop", "value": 118}, {"name": "avent", "value": 118}, {"name": "choose", "value": 118}, {"name": "In", "value": 118}, {"name": "100", "value": 118}, {"name": "stand", "value": 118}, {"name": "neck", "value": 117}, {"name": "18", "value": 117}, {"name": "purchasing", "value": 117}, {"name": "choice", "value": 117}, {"name": "version", "value": 117}, {"name": "designed", "value": 117}, {"name": "arms", "value": 117}, {"name": "saver", "value": 116}, {"name": "Works", "value": 116}, {"name": "pockets", "value": 116}, {"name": "graco", "value": 115}, {"name": "black", "value": 115}, {"name": "solid", "value": 115}, {"name": "soothing", "value": 115}, {"name": "Soothies", "value": 115}, {"name": "door", "value": 115}, {"name": "soothe", "value": 115}, {"name": "adjust", "value": 114}, {"name": "confusion", "value": 114}, {"name": "rest", "value": 114}, {"name": "reading", "value": 114}, {"name": "What", "value": 113}, {"name": "cost", "value": 113}, {"name": "designs", "value": 113}, {"name": "online", "value": 113}, {"name": "spits", "value": 113}, {"name": "lid", "value": 112}, {"name": "holder", "value": 112}, {"name": "Three", "value": 112}, {"name": "bibs", "value": 112}, {"name": "I'd", "value": 111}, {"name": "thinking", "value": 111}, {"name": "summer", "value": 111}, {"name": "sterilize", "value": 111}, {"name": "moms", "value": 111}, {"name": "mirror", "value": 111}, {"name": "told", "value": 110}, {"name": "thick", "value": 110}, {"name": "support", "value": 110}, {"name": "entire", "value": 110}, {"name": "multiple", "value": 110}, {"name": "chewing", "value": 109}, {"name": "Its", "value": 109}, {"name": "infants", "value": 109}, {"name": "save", "value": 109}, {"name": "satisfied", "value": 109}, {"name": "pay", "value": 109}, {"name": "Excellent", "value": 109}, {"name": "sons", "value": 108}, {"name": "enjoy", "value": 108}, {"name": "forward", "value": 108}, {"name": "fold", "value": 108}, {"name": "NUK", "value": 108}, {"name": "grand", "value": 107}, {"name": "soap", "value": 107}, {"name": "compared", "value": 107}, {"name": "sounds", "value": 107}, {"name": "At", "value": 106}, {"name": "nap", "value": 106}, {"name": "Thank", "value": 106}, {"name": "crying", "value": 106}, {"name": "wide", "value": 106}, {"name": "seller", "value": 106}, {"name": "kitchen", "value": 105}, {"name": "birth", "value": 105}, {"name": "baby!", "value": 105}, {"name": "dont", "value": 105}, {"name": "child's", "value": 105}, {"name": "description", "value": 104}, {"name": "body", "value": 104}, {"name": "roll", "value": 104}, {"name": "useless", "value": 104}, {"name": "it!!", "value": 104}, {"name": "Would", "value": 104}, {"name": "normal", "value": 103}, {"name": "simply", "value": 103}, {"name": "hear", "value": 102}, {"name": "touch", "value": 102}, {"name": "hates", "value": 102}, {"name": "saved", "value": 102}, {"name": "pumping", "value": 102}, {"name": "round", "value": 101}, {"name": "bassinet", "value": 101}, {"name": "cold", "value": 101}, {"name": "girls", "value": 101}, {"name": "finding", "value": 101}, {"name": "frog", "value": 101}, {"name": "brush", "value": 101}, {"name": "send", "value": 101}, {"name": "switch", "value": 101}]